{
  "sourceInformation" : {
    "url" : "http://example.org"
  },
  "reset" : true,
  "timeFrame" : {
    "startTimestamp" : 1683893404.139512000,
    "endTimestamp" : 1683893404.139492000
  },
  "nestedResponses" : [ {
    "sourceInformation" : {
      "url" : "http://example.org"
    },
    "reset" : true,
    "timeFrame" : {
      "startTimestamp" : 1683893404.139563000,
      "endTimestamp" : 1683893404.139558000
    }
  }, {
    "sourceInformation" : {
      "url" : "http://example.org"
    },
    "reset" : true,
    "timeFrame" : {
      "startTimestamp" : 1683893404.139616000,
      "endTimestamp" : 1683893404.139610000
    }
  } ]
}